{"path":"%E2%80%A0%D0%9F%D0%B0%D1%85%D0%B8%D1%82%D0%B5%D1%81%D1%82%D0%BE%D0%B2%D1%8B%D0%B5%20-%20%E2%80%A0Pachytestopsida","deepCounters":{"total":13,"images":8,"folders":5,"files":8},"counters":{"total":1,"folders":1},"thumb":{"path":"%E2%80%A0%D0%9F%D0%B0%D1%85%D0%B8%D1%82%D0%B5%D1%81%D1%82%D0%BE%D0%B2%D1%8B%D0%B5%20-%20%E2%80%A0Pachytestales\/%E2%80%A0%D0%90%D0%BB%D0%B5%D1%82%D0%BE%D0%BF%D1%82%D0%B5%D1%80%D0%B8%D0%B4%D0%BE%D0%B2%D1%8B%D0%B5%20-%20%E2%80%A0Alethopteridaceae\/%E2%80%A0%D0%90%D0%BB%D0%B5%D1%82%D0%BE%D0%BF%D1%82%D0%B5%D1%80%D0%B8%D1%81%20%D0%A1%D0%B5%D1%80%D0%BB%D0%B8%D0%B8%20-%20%E2%80%A0Alethopteris%20serlii\/thumbs\/SET09220.JPG","width":512,"height":410},"thumbCaption":"<h3>\u2020Пахитестовые - \u2020Pachytestopsida<\/h3>","album":{"description":"<br\/>\nHerbarium.INFO Herbarium Photo Collection: Ferns, Conifers, Cycads, Flowers, Trees, Mosses, Grasses, Pests and Diseases.<br\/>\n<br\/><i><b>3272<\/b> species in <b>240<\/b> families and in <b>81<\/b> orders photographed.<br\/>\n<br\/><b>39465<\/b> images total.<\/i><br\/><br\/>\nTry also other sites: <br\/>\n    <a href=\"https:\/\/herbariuminfo.netlify.app\">Herbarium.INFO<\/a>&nbsp;\u2022&nbsp;\n    <a href=\"https:\/\/plantariuminfo.netlify.app\">Plantarium.INFO<\/a>&nbsp;\u2022&nbsp;\n    <a href=\"https:\/\/fungarium.netlify.app\">Fungarium.INFO<\/a>&nbsp;\u2022&nbsp;\n    <a href=\"https:\/\/lichenarium.netlify.app\">Lichenarium.INFO<\/a>&nbsp;\u2022&nbsp;\n    <a href=\"https:\/\/algaerium.netlify.app\">Algaerium.INFO<\/a>","title":"Herbarium.INFO Herbs: Dicotyledones & Monocotyledones"},"objects":[{"path":"%E2%80%A0%D0%9F%D0%B0%D1%85%D0%B8%D1%82%D0%B5%D1%81%D1%82%D0%BE%D0%B2%D1%8B%D0%B5%20-%20%E2%80%A0Pachytestales","deepCounters":{"total":12,"images":8,"folders":4,"files":8},"counters":{"total":1,"folders":1},"thumb":{"path":"%E2%80%A0%D0%9F%D0%B0%D1%85%D0%B8%D1%82%D0%B5%D1%81%D1%82%D0%BE%D0%B2%D1%8B%D0%B5%20-%20%E2%80%A0Pachytestales\/%E2%80%A0%D0%90%D0%BB%D0%B5%D1%82%D0%BE%D0%BF%D1%82%D0%B5%D1%80%D0%B8%D0%B4%D0%BE%D0%B2%D1%8B%D0%B5%20-%20%E2%80%A0Alethopteridaceae\/%E2%80%A0%D0%90%D0%BB%D0%B5%D1%82%D0%BE%D0%BF%D1%82%D0%B5%D1%80%D0%B8%D1%81%20%D0%A1%D0%B5%D1%80%D0%BB%D0%B8%D0%B8%20-%20%E2%80%A0Alethopteris%20serlii\/thumbs\/SET09220.JPG","width":512,"height":410},"thumbCaption":"<h3>\u2020Пахитестовые - \u2020Pachytestales<\/h3>","name":"\u2020Пахитестовые - \u2020Pachytestales","dates":{"added":1714079549,"dateRange":{"0":1683279439,"1":1683279575}},"fileDate":"2024-04-26T00:12:56.845Z","category":"folder"}],"name":"\u2020Пахитестовые - \u2020Pachytestopsida","dates":{"added":1714079549,"dateRange":{"0":1683279439,"1":1683279575}},"fileDate":"2024-04-26T00:12:29.935Z"}